superdir/__init__.py
superdir/__main__.py
superdir/superdir.py
superdir/tree.py
superdir/utils.py
superdir/validator.py
superdir/walk_funcs.py
superdir-0.1.3.data/scripts/superdir
superdir-0.1.3.dist-info/DESCRIPTION.rst
superdir-0.1.3.dist-info/METADATA
superdir-0.1.3.dist-info/RECORD
superdir-0.1.3.dist-info/WHEEL
superdir-0.1.3.dist-info/metadata.json
superdir-0.1.3.dist-info/top_level.txt
