Metadata-Version: 2.0
Name: superdir
Version: 0.1.3
Summary: Turn that text file into a file tree!
Home-page: http://github.com/foundling/superdir
Author: Alex Ramsdell
Author-email: alexramsdell@gmail.com
License: MIT
Keywords: cli productivity
Platform: UNKNOWN
Classifier: License :: OSI Approved :: MIT License
Classifier: Programming Language :: Python
Classifier: Programming Language :: Python :: 2.7
Classifier: Programming Language :: Python :: 3
Requires-Dist: superdir
